{
  "products": [
    {
      "id": 1,
      "name": "Notebook Dell",
      "description": "Notebook Dell Inspiron 15, 8GB RAM, 256GB SSD",
      "price": 3500
    },
    {
      "id": 2,
      "name": "Mouse Logitech",
      "description": "Mouse sem fio Logitech MX Master 3",
      "price": 350
    },
    {
      "id": 3,
      "name": "Teclado Mecânico",
      "description": "Teclado mecânico RGB com switches Cherry MX",
      "price": 450
    },
    {
      "id": 4,
      "name": "Monitor LG",
      "description": "Monitor LG 27 polegadas, Full HD, IPS",
      "price": 1200
    },
    {
      "id": 5,
      "name": "Webcam Logitech",
      "description": "Webcam Full HD 1080p com microfone integrado",
      "price": 280
    }
  ]
}
